frypto/__init__.py
frypto/allfeatures.py
frypto/ewma.py
frypto/feature_engineering.py
frypto/helpers.py
frypto/lag_rolling.py
frypto/momentum.py
frypto/price.py
frypto/statistical_features.py
frypto/trend_features.py
frypto/utils.py
frypto/volatility.py
frypto/volume.py
frypto-0.1.3.dist-info/LICENSE
frypto-0.1.3.dist-info/METADATA
frypto-0.1.3.dist-info/WHEEL
frypto-0.1.3.dist-info/top_level.txt
frypto-0.1.3.dist-info/RECORD
