Metadata-Version: 2.1
Name: frypto
Version: 0.1.3
Summary: Crypto data feature engineering package.
Author-email: Abderlahman Elsayed <bedoelsayed785@gmail.com>
License: MIT License
Project-URL: Repository, https://github.com/NotAbdelrahmanelsayed/frypto
Project-URL: Issues, https://github.com/NotAbdelrahmanelsayed/frypto/issues
Keywords: feature engineering,cryptocurrency,crypto,time-series,technical indicators,data preprocessing,financial data,machine learning,trading,blockchain,RSI,MACD,moving average,price prediction,volatility,momentum indicators,data analysis,yfinance
Classifier: Development Status :: 4 - Beta
Classifier: Intended Audience :: Developers
Classifier: Intended Audience :: Financial and Insurance Industry
Classifier: Intended Audience :: Science/Research
Classifier: License :: OSI Approved :: MIT License
Classifier: Programming Language :: Python :: 3.7
Classifier: Programming Language :: Python :: 3.8
Classifier: Programming Language :: Python :: 3.9
Classifier: Programming Language :: Python :: 3.10
Classifier: Programming Language :: Python :: 3.11
Classifier: Programming Language :: Python :: 3.12
Classifier: Environment :: Console
Requires-Python: >=3.7
License-File: LICENSE
Requires-Dist: pandas
Requires-Dist: numpy
Requires-Dist: numba
Requires-Dist: scipy
Requires-Dist: yfinance
